blackhc/mdp/__init__.py
blackhc/mdp/example.py
blackhc/mdp/lp.py
blackhc/mdp/version.py
blackhc/mdp/dsl/__init__.py
blackhc/mdp/dsl/ast.py
blackhc/mdp/dsl/context.py
blackhc.mdp-1.0.6.dist-info/DESCRIPTION.rst
blackhc.mdp-1.0.6.dist-info/METADATA
blackhc.mdp-1.0.6.dist-info/RECORD
blackhc.mdp-1.0.6.dist-info/WHEEL
blackhc.mdp-1.0.6.dist-info/metadata.json
blackhc.mdp-1.0.6.dist-info/top_level.txt
