Metadata-Version: 2.0
Name: blackhc.mdp
Version: 1.0.6
Summary: MDP framework for the OpenAI Gym
Home-page: https://github.com/blackhc/mdp
Author: Andreas Kirsch
Author-email: blackhc+mdp@gmail.com
License: Apache
Keywords: mdp rl
Platform: UNKNOWN
Classifier: Development Status :: 5 - Production/Stable
Classifier: Intended Audience :: Developers
Classifier: Intended Audience :: Science/Research
Classifier: Topic :: Software Development :: Libraries :: Python Modules
Classifier: License :: OSI Approved :: Apache Software License
Classifier: Programming Language :: Python :: 3.3
Classifier: Programming Language :: Python :: 3.4
Classifier: Programming Language :: Python :: 3.5
Requires-Dist: gym (>=0.9.2)
Requires-Dist: ipython (>=6.1.0)
Requires-Dist: ipywidgets
Requires-Dist: matplotlib
Requires-Dist: networkx (<2.0.0,>=1.11.0)
Requires-Dist: numpy
Requires-Dist: pydotplus
Requires-Dist: typing
Provides-Extra: dev
Requires-Dist: check-manifest; extra == 'dev'
Provides-Extra: test
Requires-Dist: coverage; extra == 'test'
Requires-Dist: pytest; extra == 'test'
